digital_commons/__init__.py
digital_commons/digital_commons/__init__.py
digital_commons/digital_commons/digital_commons.py
digital_commons-0.1.0.dist-info/METADATA
digital_commons-0.1.0.dist-info/WHEEL
digital_commons-0.1.0.dist-info/RECORD
