Metadata-Version: 2.1
Name: digital-commons
Version: 0.1.0
Summary: A Python Wrapper around Digital Commons Outbound API v.2
Author: Mark Baggett
Author-email: mbagget1@utk.edu
Requires-Python: >=3.11,<4.0
Classifier: Programming Language :: Python :: 3
Classifier: Programming Language :: Python :: 3.11
Requires-Dist: requests (>=2.31.0,<3.0.0)
Requires-Dist: ruff (>=0.2.1,<0.3.0)
